pyonize/__init__.py
pyonize/__main__.py
pyonize-0.1.5.dist-info/LICENSE
pyonize-0.1.5.dist-info/WHEEL
pyonize-0.1.5.dist-info/METADATA
pyonize-0.1.5.dist-info/RECORD
