Metadata-Version: 2.1
Name: pyonize
Version: 0.1.5
Summary: convert json|dict to python object
Home-page: https://github.com/BilalAlpaslan/Pyonize
License: LICENSE
Author: Bilal Alpaslan
Author-email: m.bilal.alpaslan@gmail.com
Requires-Python: >=3.7
Classifier: License :: Other/Proprietary License
Classifier: Programming Language :: Python :: 3
Classifier: Programming Language :: Python :: 3.10
Classifier: Programming Language :: Python :: 3.7
Classifier: Programming Language :: Python :: 3.8
Classifier: Programming Language :: Python :: 3.9
